{
  "feature_cols": [
    "CLASE_ACC_norm",
    "LOCALIDAD_norm",
    "franja_horaria",
    "diseno_lugar",
    "h3_res7",
    "h3_res8",
    "grupo_causa",
    "mes",
    "dia_semana",
    "hora",
    "hora_sin",
    "hora_cos",
    "mes_sin",
    "mes_cos",
    "lat",
    "lon",
    "n_vehiculos",
    "n_actores",
    "edad_min",
    "edad_prom",
    "n_hipotesis",
    "es_fin_semana",
    "es_festivo",
    "es_finde_o_festivo",
    "involucra_moto",
    "involucra_bici",
    "involucra_bus",
    "involucra_camion",
    "involucra_peaton",
    "involucra_motociclista",
    "involucra_ciclista",
    "involucra_pasajero",
    "moto_noche",
    "peaton_interseccion",
    "bici_finde",
    "sin_dato_relacional"
  ],
  "cat_cols": [
    "CLASE_ACC_norm",
    "LOCALIDAD_norm",
    "franja_horaria",
    "diseno_lugar",
    "h3_res7",
    "h3_res8",
    "grupo_causa"
  ],
  "num_cols": [
    "mes",
    "dia_semana",
    "hora",
    "hora_sin",
    "hora_cos",
    "mes_sin",
    "mes_cos",
    "lat",
    "lon",
    "n_vehiculos",
    "n_actores",
    "edad_min",
    "edad_prom",
    "n_hipotesis"
  ],
  "bool_cols": [
    "es_fin_semana",
    "es_festivo",
    "es_finde_o_festivo",
    "involucra_moto",
    "involucra_bici",
    "involucra_bus",
    "involucra_camion",
    "involucra_peaton",
    "involucra_motociclista",
    "involucra_ciclista",
    "involucra_pasajero",
    "moto_noche",
    "peaton_interseccion",
    "bici_finde",
    "sin_dato_relacional"
  ],
  "defaults": {
    "CLASE_ACC_norm": "CHOQUE",
    "LOCALIDAD_norm": "KENNEDY",
    "franja_horaria": "Tarde",
    "diseno_lugar": "Tramo de Via",
    "h3_res7": "8766e092effffff",
    "h3_res8": "8866e09225fffff",
    "grupo_causa": "No mantener distancia",
    "mes": 7.0,
    "dia_semana": 3.0,
    "hora": 13.0,
    "hora_sin": -0.2588190451025208,
    "hora_cos": -0.4999999999999998,
    "mes_sin": -2.4492935982947064e-16,
    "mes_cos": 6.123233995736766e-17,
    "lat": 4.64523995,
    "lon": -74.1033,
    "n_vehiculos": 2.0,
    "n_actores": 2.0,
    "edad_min": 28.0,
    "edad_prom": 37.0,
    "n_hipotesis": 1.0,
    "es_fin_semana": false,
    "es_festivo": false,
    "es_finde_o_festivo": false,
    "involucra_moto": false,
    "involucra_bici": false,
    "involucra_bus": false,
    "involucra_camion": false,
    "involucra_peaton": false,
    "involucra_motociclista": false,
    "involucra_ciclista": false,
    "involucra_pasajero": false,
    "moto_noche": false,
    "peaton_interseccion": false,
    "bici_finde": false,
    "sin_dato_relacional": false
  },
  "clase": [
    "ATROPELLO",
    "AUTOLESION",
    "CAIDA DE OCUPANTE",
    "CHOQUE",
    "INCENDIO",
    "OTRO",
    "VOLCAMIENTO"
  ],
  "localidad": [
    "ANTONIO NARINO",
    "BARRIOS UNIDOS",
    "BOSA",
    "CANDELARIA",
    "CHAPINERO",
    "CIUDAD BOLIVAR",
    "ENGATIVA",
    "FONTIBON",
    "KENNEDY",
    "LOS MARTIRES",
    "PUENTE ARANDA",
    "RAFAEL URIBE URIBE",
    "SAN CRISTOBAL",
    "SANTA FE",
    "SUBA",
    "SUMAPAZ",
    "TEUSAQUILLO",
    "TUNJUELITO",
    "USAQUEN",
    "USME"
  ],
  "causa": [
    "Adelantamiento indebido",
    "Conducta del peatón",
    "Desobedecer señales/prelación",
    "Embriaguez/sustancias",
    "Exceso de velocidad",
    "Maniobra/giro imprudente",
    "No mantener distancia",
    "Otra / no especificada",
    "Sin dato"
  ]
}